<annotation>
	<folder>orange</folder>
	<filename>orange (6).JPG</filename>
	<path>C:\Users\DELL\Desktop\Thesis\F1\orange\orange (6).JPG</path>
	<source>
		<database>Unknown</database>
	</source>
	<size>
		<width>4032</width>
		<height>3024</height>
		<depth>3</depth>
	</size>
	<segmented>0</segmented>
	<object>
		<name>orange</name>
		<pose>Unspecified</pose>
		<truncated>0</truncated>
		<difficult>0</difficult>
		<bndbox>
			<xmin>146</xmin>
			<ymin>21</ymin>
			<xmax>3975</xmax>
			<ymax>2992</ymax>
		</bndbox>
	</object>
</annotation>
